apisec/__int__.py
apisec/__main__.py
apisec/graphql.py
apisec/init.py
apisec/rest.py
apisec/soap.py
apisec-1.0.dist-info/LICENSE
apisec-1.0.dist-info/METADATA
apisec-1.0.dist-info/WHEEL
apisec-1.0.dist-info/entry_points.txt
apisec-1.0.dist-info/top_level.txt
apisec-1.0.dist-info/RECORD
