Metadata-Version: 2.1
Name: apisec
Version: 1.0
Summary: API Security Testing Tool
Home-page: https://github.com/vkvbit/apisec
Download-URL: https://github.com/vkvbit/apisec/archive/refs/tags/1.0.zip
Author: Vaibhav Kumar
Author-email: Vaibhav Kumar <myselfv@hotmail.com>
License: MIT
Project-URL: homepage, https://github.com/vkvbit/apisec
Project-URL: download_url, https://github.com/vkvbit/apisec/archive/refs/tags/1.0.zip
Keywords: apisec,rest,graphql,soap,restful,api,security,scanner,tool,vulnerability
Classifier: Intended Audience :: Developers
Classifier: Natural Language :: English
Classifier: Programming Language :: Python :: 3
Classifier: Programming Language :: Python :: 3.6
Classifier: Programming Language :: Python :: 3.7
Classifier: Programming Language :: Python :: 3.8
Classifier: Programming Language :: Python :: 3.9
Classifier: Topic :: Security
Classifier: Topic :: Software Development :: Libraries :: Python Modules
License-File: LICENSE
